cjoin.cpython-38-darwin.so
wombat/__init__.py
wombat/engine/__init__.py
wombat/engine/engine.py
wombat/engine/nodes.py
wombat/engine/sql.py
wombat/engine/udf.py
wombat/ml/__init__.py
wombat/ml/clean.py
wombat/ops/__init__.py
wombat/ops/cjoin.c
wombat/ops/group.py
wombat/ops/helpers.py
wombat/ops/join.py
wombat/ops/ops.py
wombat/ops/parse.py
wombat/ops/table.py
wombat_db/__init__.py
wombat_db/engine/__init__.py
wombat_db/engine/column.py
wombat_db/engine/engine.py
wombat_db/engine/nodes.py
wombat_db/engine/sql.py
wombat_db/engine/udf.py
wombat_db/ml/__init__.py
wombat_db/ml/clean.py
wombat_db/ops/__init__.py
wombat_db/ops/cjoin.c
wombat_db/ops/group.py
wombat_db/ops/helpers.py
wombat_db/ops/join.py
wombat_db/ops/ops.py
wombat_db/ops/parse.py
wombat_db/ops/table.py
wombat_db-0.0.18.dist-info/LICENSE
wombat_db-0.0.18.dist-info/METADATA
wombat_db-0.0.18.dist-info/WHEEL
wombat_db-0.0.18.dist-info/top_level.txt
wombat_db-0.0.18.dist-info/RECORD
