Metadata-Version: 2.1
Name: wombat-db
Version: 0.0.18
Summary: Useful data crunching tools for pyarrow
Home-page: https://github.com/TomScheffers/wombat
Author: Tom Scheffers
Author-email: tom@youngbulls.nl 
License: APACHE
Download-URL: https://pypi.org/project/wombat-db/
Keywords: arrow,pyarrow,data,sql,dataframe
Platform: UNKNOWN
Requires-Dist: numpy (>=1.19.2)
Requires-Dist: pyarrow (>=5.0.0)
